pret/ui/markdown/__init__.py
pret/ui/markdown/js-extension/package.json
pret/ui/markdown/js-extension/schemas/pret-markdown/package.json.orig
pret/ui/markdown/js-extension/static/214.b4d0cfa38b36cb2c50b3.js
pret/ui/markdown/js-extension/static/38.345d3c84063487ff6b9a.js
pret/ui/markdown/js-extension/static/38.345d3c84063487ff6b9a.js.LICENSE.txt
pret/ui/markdown/js-extension/static/81.8c0a5bb6f6f6181a2efe.js
pret/ui/markdown/js-extension/static/remoteEntry.ce78bae4d5efb7a2ec21.js
pret/ui/markdown/js-extension/static/style.js
pret/ui/markdown/js-extension/static/third-party-licenses.json
pret_markdown-10.1.0.post1.data/data/share/jupyter/labextensions/pret-markdown/package.json
pret_markdown-10.1.0.post1.data/data/share/jupyter/labextensions/pret-markdown/schemas/pret-markdown/package.json.orig
pret_markdown-10.1.0.post1.data/data/share/jupyter/labextensions/pret-markdown/static/214.b4d0cfa38b36cb2c50b3.js
pret_markdown-10.1.0.post1.data/data/share/jupyter/labextensions/pret-markdown/static/38.345d3c84063487ff6b9a.js
pret_markdown-10.1.0.post1.data/data/share/jupyter/labextensions/pret-markdown/static/38.345d3c84063487ff6b9a.js.LICENSE.txt
pret_markdown-10.1.0.post1.data/data/share/jupyter/labextensions/pret-markdown/static/81.8c0a5bb6f6f6181a2efe.js
pret_markdown-10.1.0.post1.data/data/share/jupyter/labextensions/pret-markdown/static/remoteEntry.ce78bae4d5efb7a2ec21.js
pret_markdown-10.1.0.post1.data/data/share/jupyter/labextensions/pret-markdown/static/style.js
pret_markdown-10.1.0.post1.data/data/share/jupyter/labextensions/pret-markdown/static/third-party-licenses.json
pret_markdown-10.1.0.post1.dist-info/METADATA
pret_markdown-10.1.0.post1.dist-info/WHEEL
pret_markdown-10.1.0.post1.dist-info/licenses/LICENSE
pret_markdown-10.1.0.post1.dist-info/RECORD
