Metadata-Version: 2.4
Name: pret-markdown
Version: 10.1.0.post1
Summary: Markdown renderer plugin for Pret
Project-URL: homepage, https://github.com/percevalw/pret/
Project-URL: repository, https://github.com/percevalw/pret/
Project-URL: documentation, https://percevalw.github.io/pret/
Author-email: Perceval Wajsbürt <perceval.wajsburt@gmail.com>
License:                                  Apache License
License-File: LICENSE
Requires-Python: <4.0,>=3.7
Requires-Dist: pret
Provides-Extra: dev
Requires-Dist: hatch-jupyter-builder; extra == 'dev'
Requires-Dist: hatchling; extra == 'dev'
